pycap/__init__.py
pycap/analysis_project.py
pycap/pycap_exceptions.py
pycap/solutions.py
pycap/test_calcs.py
pycap/utilities.py
pycap/wells.py
pycap/tests/__init__.py
pycap_dss-1.3.0.dist-info/licenses/LICENSE.md
pycap_dss-1.3.0.dist-info/METADATA
pycap_dss-1.3.0.dist-info/WHEEL
pycap_dss-1.3.0.dist-info/top_level.txt
pycap_dss-1.3.0.dist-info/RECORD
